LICENSE
README.md
setup.py
src/miRBench/__init__.py
src/miRBench/dataset.py
src/miRBench/encoder.py
src/miRBench/predictor.py
src/miRBench.egg-info/PKG-INFO
src/miRBench.egg-info/SOURCES.txt
src/miRBench.egg-info/dependency_links.txt
src/miRBench.egg-info/requires.txt
src/miRBench.egg-info/top_level.txt