Metadata-Version: 2.1
Name: miRBench
Version: 0.1.1
Summary: A collection of datasets and predictors for benchmarking miRNA target site prediction algorithms
Home-page: https://github.com/katarinagresova/miRBench
Author: Katarina Gresova
Author-email: gresova11@gmail.com
License: MIT
Keywords: miRNA,target site prediction,benchmarking
License-File: LICENSE
Requires-Dist: biopython>=1.79
Requires-Dist: viennarna>=2.4.14
Requires-Dist: torch>=1.9.0
Requires-Dist: tensorflow==2.13.1
Requires-Dist: numpy==1.24.3
Requires-Dist: pandas==2.0.3
